information_linking_queries/__init__.py
information_linking_queries/dbpedia.py
information_linking_queries/headers.py
information_linking_queries/helpers.py
information_linking_queries/information_linking_apis.py
information_linking_queries/information_linking_orcid.py
information_linking_queries/orcid.py
information_linking_queries/wikidata.py
information_linking_queries/wikipedia.py
information_linking_queries-0.1.6.dist-info/METADATA
information_linking_queries-0.1.6.dist-info/WHEEL
information_linking_queries-0.1.6.dist-info/top_level.txt
information_linking_queries-0.1.6.dist-info/RECORD
