Metadata-Version: 2.1
Name: information-linking--queries
Version: 0.1.6
Summary: A library for enriching metadata through semantic queries. It performs API calls to Wikipedia, Wikidata, DBpedia, and ORCID to retrieve and integrate structured information from multiple open knowledge sources.
Author: Nikolas Kapralos
Project-URL: GitHub, https://github.com/Digital-Methods-for-Knowledge-Graphs/information-linking-queries-python-library
Requires-Python: >=3.11
Requires-Dist: requests
Requires-Dist: SPARQLWrapper==2.0.0
